doordeck_headless_sdk/Doordeck.Headless.Sdk.dll
doordeck_headless_sdk/__init__.py
doordeck_headless_sdk/_doordeck_headless_sdk.pyd
doordeck_headless_sdk/doordeck_headless_sdk.py
doordeck_headless_sdk-0.188.0.dist-info/licenses/LICENSE
doordeck_headless_sdk-0.188.0.dist-info/METADATA
doordeck_headless_sdk-0.188.0.dist-info/WHEEL
doordeck_headless_sdk-0.188.0.dist-info/top_level.txt
doordeck_headless_sdk-0.188.0.dist-info/RECORD
