Metadata-Version: 2.4
Name: doordeck_headless_sdk
Version: 0.188.0
Summary: The official Doordeck SDK for Kotlin Multiplatform
Author-email: Doordeck Limited <development@doordeck.com>
Project-URL: Homepage, https://www.doordeck.com
Project-URL: Source, https://github.com/doordeck/doordeck-headless-sdk.git
Project-URL: Issue tracker, https://github.com/doordeck/doordeck-headless-sdk/issues
Keywords: doordeck,sdk,access control
Classifier: Development Status :: 3 - Alpha
Classifier: Programming Language :: Python :: 3.13
Classifier: Operating System :: Microsoft :: Windows
Requires-Python: ==3.13.2
License-File: LICENSE
Dynamic: license-file
